myflixer/__init__.py
myflixer/__main__.py
myflixer/flix.py
myflixer-0.0.1b0.dist-info/LICENSE
myflixer-0.0.1b0.dist-info/METADATA
myflixer-0.0.1b0.dist-info/WHEEL
myflixer-0.0.1b0.dist-info/top_level.txt
myflixer-0.0.1b0.dist-info/RECORD
