Metadata-Version: 2.1
Name: myflixer
Version: 0.0.1b0
Summary: Myflixer
Author-email: yusef <yusef314159@gmail.com>
License: Copyright (c) 2018 The Python Packaging Authority        
Project-URL: Homepage, https://github.com/mexusef/myflixer
Project-URL: Bug Tracker, https://github.com/mexusef/myflixer/issues
Classifier: Programming Language :: Python :: 3
Classifier: License :: OSI Approved :: MIT License
Classifier: Operating System :: OS Independent
Requires-Python: >=3.9
License-File: LICENSE
Requires-Dist: PyQt5 (~=5.15.6)
Requires-Dist: PyQtWebEngine (~=5.15.5)
Requires-Dist: beautifulsoup4 (~=4.10.0)
Requires-Dist: requests (~=2.28.1)
